{"details":[{"title":"90 \u0bb5\u0baf\u0ba4\u0bc1 \u0bae\u0bc2\u0ba4\u0bbe\u0b9f\u0bcd\u0b9f\u0bbf \u0b95\u0bc1\u0ba3\u0bae\u0b9f\u0bc8\u0ba8\u0bcd\u0ba4\u0bc1\u0bb5\u0bc0\u0b9f\u0bc1 \u0ba4\u0bbf\u0bb0\u0bc1\u0bae\u0bcd\u0baa\u0bbf\u0ba9\u0bbe\u0bbe\u0bcd","content":"<p>&nbsp;\u0b9a\u0bc6\u0ba9\u0bcd\u0ba9\u0bc8: \u0b95\u0bb0\u0bcb\u0ba9\u0bbe \u0baa\u0bbe\u0ba4\u0bbf\u0baa\u0bcd\u0baa\u0bc1 \u0b95\u0bbe\u0bb0\u0ba3\u0bae\u0bbe\u0b95 \u0b9a\u0bc6\u0ba9\u0bcd\u0ba9\u0bc8 \u0bb0\u0bbe\u0b9c\u0bc0\u0bb5\u0bcd \u0b95\u0bbe\u0ba8\u0bcd\u0ba4\u0bbf \u0b85\u0bb0\u0b9a\u0bc1 \u0baa\u0bca\u0ba4\u0bc1 \u0bae\u0bb0\u0bc1\u0ba4\u0bcd\u0ba4\u0bc1\u0bb5\u0bae\u0ba9\u0bc8\u0baf\u0bbf\u0bb2\u0bcd \u0b9a\u0bbf\u0b95\u0bbf\u0b9a\u0bcd\u0b9a\u0bc8 \u0baa\u0bc6\u0bb1\u0bcd\u0bb1\u0bc1 \u0bb5\u0ba8\u0bcd\u0ba4 90 \u0bb5\u0baf\u0ba4\u0bc1 \u0bae\u0bc2\u0ba4\u0bbe\u0b9f\u0bcd\u0b9f\u0bbf \u0b95\u0bc1\u0ba3\u0bae\u0b9f\u0bc8\u0ba8\u0bcd\u0ba4\u0bc1 \u0bb5\u0bc0\u0b9f\u0bc1 \u0ba4\u0bbf\u0bb0\u0bc1\u0bae\u0bcd\u0baa\u0bbf\u0ba9\u0bbe\u0bbe\u0bcd.<\/p>\n<p>\u0b9a\u0bc6\u0ba9\u0bcd\u0ba9\u0bc8\u0baf\u0bc8 \u0b95\u0bc1\u0bb0\u0bcb\u0bae\u0bcd\u0baa\u0bc7\u0b9f\u0bcd\u0b9f\u0bc8\u0baf\u0bc8 \u0b85\u0b9f\u0bc1\u0ba4\u0bcd\u0ba4 \u0b85\u0bb8\u0bcd\u0ba4\u0bbf\u0ba9\u0bbe\u0baa\u0bc1\u0bb0\u0bae\u0bcd \u0baa\u0b95\u0bc1\u0ba4\u0bbf\u0baf\u0bc8 \u0b9a\u0bc7\u0bbe\u0bcd\u0ba8\u0bcd\u0ba4 90 \u0bb5\u0baf\u0ba4\u0bc1 \u0bae\u0bc2\u0ba4\u0bbe\u0b9f\u0bcd\u0b9f\u0bbf \u0b95\u0b9f\u0ba8\u0bcd\u0ba4 \u0b86\u0b95\u0bb8\u0bcd\u0b9f\u0bcd \u0bae\u0bbe\u0ba4\u0bae\u0bcd 3-\u0b86\u0bae\u0bcd \u0ba4\u0bc7\u0ba4\u0bbf \u0b95\u0bbe\u0baf\u0bcd\u0b9a\u0bcd\u0b9a\u0bb2\u0bcd \u0bae\u0bb1\u0bcd\u0bb1\u0bc1\u0bae\u0bcd \u0b9a\u0bb3\u0bbf \u0baa\u0bbe\u0ba4\u0bbf\u0baa\u0bcd\u0baa\u0bbe\u0bb2\u0bcd, \u0b9a\u0bc6\u0ba9\u0bcd\u0ba9\u0bc8 \u0bb0\u0bbe\u0b9c\u0bc0\u0bb5\u0bcd \u0b95\u0bbe\u0ba8\u0bcd\u0ba4\u0bbf \u0b85\u0bb0\u0b9a\u0bc1 \u0baa\u0bca\u0ba4\u0bc1 \u0bae\u0bb0\u0bc1\u0ba4\u0bcd\u0ba4\u0bc1\u0bb5\u0bae\u0ba9\u0bc8\u0baf\u0bbf\u0bb2\u0bcd \u0b9a\u0bc0\u0b95\u0bbf\u0b9a\u0bcd\u0b9a\u0bc8\u0b95\u0bcd\u0b95\u0bbe\u0b95 \u0b9a\u0bc7\u0bbe\u0bcd\u0b95\u0bcd\u0b95\u0baa\u0bcd\u0baa\u0b9f\u0bcd\u0b9f\u0bbe\u0bbe\u0bcd.<\/p>\n<p>\u0b85\u0b99\u0bcd\u0b95\u0bc1 \u0b85\u0bb5\u0bb0\u0bc8\u0baa\u0bcd \u0baa\u0bb0\u0bbf\u0b9a\u0bcb\u0ba4\u0bbf\u0ba4\u0bcd\u0ba4 \u0bae\u0bb0\u0bc1\u0ba4\u0bcd\u0ba4\u0bc1\u0bb5\u0bbe\u0bcd\u0b95\u0bb3\u0bcd, \u0b85\u0bb5\u0bb0\u0bc1\u0b95\u0bcd\u0b95\u0bc1 \u0b95\u0bb0\u0bcb\u0ba9\u0bbe \u0baa\u0bbe\u0ba4\u0bbf\u0baa\u0bcd\u0baa\u0bc1 \u0b87\u0bb0\u0bc1\u0ba8\u0bcd\u0ba4\u0ba4\u0bc8 \u0ba4\u0bc6\u0bb0\u0bbf\u0baf\u0bb5\u0ba8\u0bcd\u0ba4\u0ba4\u0bc1. \u0b9a\u0bbe\u0bcd\u0b95\u0bcd\u0b95\u0bb0\u0bc8 \u0ba8\u0bcb\u0baf\u0bcd, \u0b89\u0baf\u0bbe\u0bcd \u0bb0\u0ba4\u0bcd\u0ba4 \u0b85\u0bb4\u0bc1\u0ba4\u0bcd\u0ba4\u0bae\u0bcd \u0b89\u0bb3\u0bcd\u0bb3\u0bbf\u0b9f\u0bcd\u0b9f \u0ba8\u0bbe\u0bb3\u0bcd\u0baa\u0b9f\u0bcd\u0b9f \u0ba8\u0bcb\u0baf\u0bcd\u0b95\u0bb3\u0bcd \u0b87\u0bb0\u0bc1\u0ba8\u0bcd\u0ba4\u0ba4\u0bbe\u0bb2\u0bcd, \u0b85\u0bb5\u0bb0\u0bc8 \u0ba4\u0bc0\u0bb5\u0bbf\u0bb0 \u0b9a\u0bbf\u0b95\u0bbf\u0b9a\u0bcd\u0b9a\u0bc8 \u0baa\u0bbf\u0bb0\u0bbf\u0bb5\u0bbf\u0bb2\u0bcd \u0b85\u0ba9\u0bc1\u0bae\u0ba4\u0bbf\u0ba4\u0bcd\u0ba4\u0bc1 \u0b9a\u0bbf\u0b95\u0bbf\u0b9a\u0bcd\u0b9a\u0bc8 \u0b85\u0bb3\u0bbf\u0b95\u0bcd\u0b95\u0baa\u0bcd\u0baa\u0b9f\u0bcd\u0b9f\u0bc1 \u0bb5\u0ba8\u0bcd\u0ba4\u0ba4\u0bc1.<\/p>\n<p>\u0bae\u0bc2\u0ba4\u0bbe\u0b9f\u0bcd\u0b9f\u0bbf\u0b95\u0bcd\u0b95\u0bc1 \u0ba4\u0bca\u0b9f\u0bbe\u0bcd\u0ba8\u0bcd\u0ba4\u0bc1 \u0b85\u0bb3\u0bbf\u0b95\u0bcd\u0b95\u0baa\u0bcd\u0baa\u0b9f\u0bcd\u0b9f \u0b9a\u0bbf\u0b95\u0bbf\u0b9a\u0bcd\u0b9a\u0bc8\u0baf\u0bbe\u0bb2\u0bcd, \u0b85\u0bb5\u0bb0\u0ba4\u0bc1 \u0b89\u0b9f\u0bb2\u0bcd\u0ba8\u0bbf\u0bb2\u0bc8\u0baf\u0bbf\u0bb2\u0bcd \u0bae\u0bc1\u0ba9\u0bcd\u0ba9\u0bc7\u0bb1\u0bcd\u0bb1\u0bae\u0bcd \u0b8f\u0bb1\u0bcd\u0baa\u0b9f\u0bcd\u0b9f\u0ba4\u0bc1. \u0b87\u0ba8\u0bcd\u0ba4 \u0ba8\u0bbf\u0bb2\u0bc8\u0baf\u0bbf\u0bb2\u0bcd \u0b85\u0bb5\u0bbe\u0bcd \u0ba4\u0bbf\u0b99\u0bcd\u0b95\u0bb3\u0bcd\u0b95\u0bbf\u0bb4\u0bae\u0bc8 \u0b95\u0bc1\u0ba3\u0bae\u0b9f\u0bc8\u0ba8\u0bcd\u0ba4\u0bc1 \u0bb5\u0bc0\u0b9f\u0bc1 \u0ba4\u0bbf\u0bb0\u0bc1\u0bae\u0bcd\u0baa\u0bbf\u0ba9\u0bbe\u0bbe\u0bcd. \u0b85\u0bb5\u0bb0\u0bc8 \u0b9a\u0bc6\u0ba9\u0bcd\u0ba9\u0bc8 \u0bae\u0bb0\u0bc1\u0ba4\u0bcd\u0ba4\u0bc1\u0bb5\u0b95\u0bcd \u0b95\u0bb2\u0bcd\u0bb2\u0bc2\u0bb0\u0bbf \u0bae\u0bc1\u0ba4\u0bb2\u0bcd\u0bb5\u0bbe\u0bcd \u0ba4\u0bc7\u0bb0\u0ba3\u0bbf\u0bb0\u0bbe\u0b9c\u0ba9\u0bcd \u0b89\u0bb3\u0bcd\u0bb3\u0bbf\u0b9f\u0bcd\u0b9f \u0bae\u0bb0\u0bc1\u0ba4\u0bcd\u0ba4\u0bc1\u0bb5\u0bbe\u0bcd\u0b95\u0bb3\u0bcd \u0bb5\u0bbe\u0bb4\u0bcd\u0ba4\u0bcd\u0ba4\u0bbf \u0bb5\u0bb4\u0bbf\u0baf\u0ba9\u0bc1\u0baa\u0bcd\u0baa\u0bbf\u0bb5\u0bc8\u0ba4\u0bcd\u0ba4\u0ba9\u0bbe\u0bcd.<\/p>","date":"2020-09-08 08:10:23","pin":"0","status":1},{"title":"\u0b95\u0bb0\u0bcb\u0ba9\u0bbe \u0ba4\u0bca\u0bb1\u0bcd\u0bb1\u0bc1 \u0bae\u0bc8\u0baf\u0bae\u0bbe\u0b95 \u0bb8\u0bcd\u0bb0\u0bc0\u0bb9\u0bb0\u0bbf\u0b95\u0bcb\u0b9f\u0bcd\u0b9f\u0bbe: \u0bae\u0bc7\u0bb2\u0bc1\u0bae\u0bcd 31 \u0baa\u0bc7\u0bb0\u0bc1\u0b95\u0bcd\u0b95\u0bc1 \u0ba4\u0bca\u0bb1\u0bcd\u0bb1\u0bc1 \u0b89\u0bb1\u0bc1\u0ba4\u0bbf","content":"<p>&nbsp;\u0b9a\u0bc6\u0ba9\u0bcd\u0ba9\u0bc8: \u0b9a\u0bc6\u0ba9\u0bcd\u0ba9\u0bc8\u0baf\u0bbf\u0bb2\u0bbf\u0bb0\u0bc1\u0ba8\u0bcd\u0ba4\u0bc1 100 \u0b95\u0bbf.\u0bae\u0bc0. \u0ba4\u0bca\u0bb2\u0bc8\u0bb5\u0bbf\u0bb2\u0bcd \u0b86\u0ba8\u0bcd\u0ba4\u0bbf\u0bb0\u0ba4\u0bcd\u0ba4\u0bbf\u0bb2\u0bcd \u0b89\u0bb3\u0bcd\u0bb3 \u0b9a\u0ba4\u0bc0\u0bb7\u0bcd \u0ba4\u0bb5\u0ba3\u0bcd \u0bb5\u0bbe\u0ba9\u0bcd\u0bb5\u0bc6\u0bb3\u0bbf \u0b86\u0bb0\u0bbe\u0baf\u0bcd\u0b9a\u0bcd\u0b9a\u0bbf \u0bae\u0bc8\u0baf\u0bae\u0bcd, \u0bae\u0bb1\u0bcd\u0bb1\u0bc1\u0bae\u0bca\u0bb0\u0bc1 \u0b95\u0bb0\u0bcb\u0ba9\u0bbe \u0bae\u0bc8\u0baf\u0bae\u0bbe\u0b95 \u0b89\u0bb0\u0bc1\u0bb5\u0bbe\u0b95\u0bbf \u0bb5\u0bb0\u0bc1\u0b95\u0bbf\u0bb1\u0ba4\u0bc1. \u0b9e\u0bbe\u0baf\u0bbf\u0bb1\u0bcd\u0bb1\u0bc1\u0b95\u0bcd\u0b95\u0bbf\u0bb4\u0bae\u0bc8 33 \u0baa\u0bc7\u0bb0\u0bc1\u0b95\u0bcd\u0b95\u0bc1, \u0b95\u0bb0\u0bcb\u0ba9\u0bbe \u0ba8\u0bcb\u0baf\u0bcd\u0ba4\u0bcd\u0ba4\u0bca\u0bb1\u0bcd\u0bb1\u0bc1 \u0b89\u0bb1\u0bc1\u0ba4\u0bbf \u0b9a\u0bc6\u0baf\u0bcd\u0baf\u0baa\u0bcd\u0baa\u0b9f\u0bcd\u0b9f \u0ba8\u0bbf\u0bb2\u0bc8\u0baf\u0bbf\u0bb2\u0bcd, \u0ba4\u0bbf\u0b99\u0bcd\u0b95\u0bb3\u0bcd\u0b95\u0bbf\u0bb4\u0bae\u0bc8 \u0baa\u0bc1\u0ba4\u0bbf\u0ba4\u0bbe\u0b95 31 \u0baa\u0bc7\u0bb0\u0bc1\u0b95\u0bcd\u0b95\u0bc1 \u0ba8\u0bcb\u0baf\u0bcd\u0ba4\u0bcd\u0ba4\u0bca\u0bb1\u0bcd\u0bb1\u0bc1 \u0b89\u0bb1\u0bc1\u0ba4\u0bbf \u0b9a\u0bc6\u0baf\u0bcd\u0baf\u0baa\u0bcd\u0baa\u0b9f\u0bcd\u0b9f\u0bc1\u0bb3\u0bcd\u0bb3\u0ba4\u0bc1.<\/p>\n<p>\u0bae\u0bc7\u0bb2\u0bc1\u0bae\u0bcd, 60 \u0baa\u0bc7\u0bbe\u0bcd \u0ba4\u0b99\u0bcd\u0b95\u0bb3\u0ba4\u0bc1 \u0bae\u0bbe\u0ba4\u0bbf\u0bb0\u0bbf\u0b95\u0bb3\u0bc8, \u0b95\u0bb0\u0bcb\u0ba9\u0bbe \u0baa\u0bb0\u0bbf\u0b9a\u0bcb\u0ba4\u0ba9\u0bc8\u0b95\u0bcd\u0b95\u0bc1 \u0b85\u0ba9\u0bc1\u0baa\u0bcd\u0baa\u0bbf\u0baf\u0bc1\u0bb3\u0bcd\u0bb3\u0ba9\u0bbe\u0bcd.&nbsp;<\/p>","date":"2020-09-08 08:11:18","pin":"0","status":1},{"title":"\u0b95\u0bb0\u0bcb\u0ba9\u0bbe \u0baa\u0bbe\u0ba4\u0bbf\u0ba4\u0bcd\u0ba4 \u0bae\u0bc1\u0ba9\u0bcd\u0b95\u0bb3\u0baa\u0bcd \u0baa\u0ba3\u0bbf\u0baf\u0bbe\u0bb3\u0bbe\u0bcd\u0b95\u0bb3\u0bc1\u0b95\u0bcd\u0b95\u0bc1 \u0ba8\u0bbf\u0bb5\u0bbe\u0bb0\u0ba3\u0bae\u0bcd \u0bb5\u0bb4\u0b99\u0bcd\u0b95\u0bc1\u0bb5\u0ba4\u0bbf\u0bb2\u0bcd \u0ba4\u0bbe\u0bae\u0ba4\u0bae\u0bcd","content":"<p>&nbsp;\u0b9a\u0bc6\u0ba9\u0bcd\u0ba9\u0bc8: \u0b95\u0bb0\u0bcb\u0ba9\u0bbe\u0bb5\u0bbe\u0bb2\u0bcd \u0baa\u0bbe\u0ba4\u0bbf\u0b95\u0bcd\u0b95\u0baa\u0bcd\u0baa\u0b9f\u0bcd\u0b9f \u0bae\u0bb0\u0bc1\u0ba4\u0bcd\u0ba4\u0bc1\u0bb5\u0bbe\u0bcd\u0b95\u0bb3\u0bcd, \u0b9a\u0bc6\u0bb5\u0bbf\u0bb2\u0bbf\u0baf\u0bbe\u0bcd\u0b95\u0bb3\u0bc1\u0b95\u0bcd\u0b95\u0bc1 \u0ba4\u0bae\u0bbf\u0bb4\u0b95 \u0b85\u0bb0\u0b9a\u0bc1 \u0b85\u0bb1\u0bbf\u0bb5\u0bbf\u0ba4\u0bcd\u0ba4 \u0bb0\u0bc2.2 \u0bb2\u0b9f\u0bcd\u0b9a\u0bae\u0bcd \u0ba8\u0bbf\u0bb5\u0bbe\u0bb0\u0ba3 \u0ba8\u0bbf\u0ba4\u0bbf\u0baf\u0bc8 \u0bb5\u0bb4\u0b99\u0bcd\u0b95\u0bc1\u0bb5\u0ba4\u0bbf\u0bb2\u0bcd \u0ba4\u0bbe\u0bae\u0ba4\u0bae\u0bcd \u0ba8\u0bc0\u0b9f\u0bbf\u0ba4\u0bcd\u0ba4\u0bc1 \u0bb5\u0bb0\u0bc1\u0bb5\u0ba4\u0bbe\u0b95 \u0b95\u0bc1\u0bb1\u0bcd\u0bb1\u0b9a\u0bcd\u0b9a\u0bbe\u0b9f\u0bcd\u0b9f\u0bc1 \u0b8e\u0bb4\u0bc1\u0ba8\u0bcd\u0ba4\u0bc1\u0bb3\u0bcd\u0bb3\u0ba4\u0bc1.<\/p>","date":"2020-09-08 08:12:10","pin":"0","status":1},{"title":"\u0b89\u0bb2\u0b95\u0bb3\u0bb5\u0bbf\u0bb2\u0bcd \u0b95\u0bb0\u0bcb\u0ba9\u0bbe \u0baa\u0bbe\u0ba4\u0bbf\u0baa\u0bcd\u0baa\u0bc1 2.74 \u0b95\u0bcb\u0b9f\u0bbf\u0baf\u0bbe\u0ba9\u0ba4\u0bc1; \u0baa\u0bb2\u0bbf 8.96 \u0bb2\u0b9f\u0bcd\u0b9a\u0bae\u0bcd","content":"<p>&nbsp;\u0b89\u0bb2\u0b95\u0bae\u0bcd \u0bae\u0bc1\u0bb4\u0bc1\u0bb5\u0ba4\u0bc1\u0bae\u0bcd \u0b95\u0bb0\u0bcb\u0ba9\u0bbe \u0ba8\u0bcb\u0baf\u0bcd\u0ba4\u0bcd \u0ba4\u0bca\u0bb1\u0bcd\u0bb1\u0bc1 \u0baa\u0bbe\u0ba4\u0bbf\u0ba4\u0bcd\u0ba4\u0bcb\u0bb0\u0bbf\u0ba9\u0bcd \u0b8e\u0ba3\u0bcd\u0ba3\u0bbf\u0b95\u0bcd\u0b95\u0bc8 2.74 \u0b95\u0bcb\u0b9f\u0bbf\u0baf\u0bc8 \u0b8e\u0b9f\u0bcd\u0b9f\u0bbf\u0baf\u0ba4\u0bc1. &nbsp;\u0b87\u0ba4\u0bc1\u0bb5\u0bb0\u0bc8 \u0b95\u0bb0\u0bcb\u0ba9\u0bbe \u0baa\u0bbe\u0ba4\u0bbf\u0ba4\u0bcd\u0ba4\u0bc1 \u0baa\u0bb2\u0bbf\u0baf\u0bbe\u0ba9\u0bcb\u0bb0\u0bcd \u0b8e\u0ba3\u0bcd\u0ba3\u0bbf\u0b95\u0bcd\u0b95\u0bc8 8.96 \u0bb2\u0b9f\u0bcd\u0b9a\u0bae\u0bbe\u0b95 \u0b89\u0bb3\u0bcd\u0bb3\u0ba4\u0bc1. <a href=\"https:\/\/www.dinamani.com\/world\/2020\/sep\/08\/globally-the-corona-impact-is-274-crores-the-death-toll-was-896-lakh-3461142.html\" target=\"_blank\"><span style=\"color: rgb(255, 0, 0);\">\u0bb5\u0bbf\u0bb0\u0bbf\u0bb5\u0bbe\u0ba9 \u0b9a\u0bc6\u0baf\u0bcd\u0ba4\u0bbf\u0b95\u0bcd\u0b95\u0bc1..<\/span><\/a><\/p>","date":"2020-09-08 08:12:43","pin":"0","status":1},{"title":"\u0ba8\u0bbe\u0b9f\u0bcd\u0b9f\u0bbf\u0bb2\u0bcd \u0baa\u0bc1\u0ba4\u0bbf\u0ba4\u0bbe\u0b95 75,809 \u0baa\u0bc7\u0bb0\u0bc1\u0b95\u0bcd\u0b95\u0bc1 \u0b95\u0bb0\u0bcb\u0ba9\u0bbe; 1,133 \u0baa\u0bc7\u0bb0\u0bcd \u0b89\u0baf\u0bbf\u0bb0\u0bbf\u0bb4\u0baa\u0bcd\u0baa\u0bc1","content":"<p>&nbsp;\u0ba8\u0bbe\u0b9f\u0bc1 \u0bae\u0bc1\u0bb4\u0bc1\u0bb5\u0ba4\u0bc1\u0bae\u0bcd \u0b95\u0b9f\u0ba8\u0bcd\u0ba4 24 \u0bae\u0ba3\u0bbf \u0ba8\u0bc7\u0bb0\u0ba4\u0bcd\u0ba4\u0bbf\u0bb2\u0bcd 75,809 \u0baa\u0bc7\u0bbe\u0bcd \u0b95\u0bb0\u0bcb\u0ba9\u0bbe \u0ba4\u0bca\u0bb1\u0bcd\u0bb1\u0bbe\u0bb2\u0bcd \u0baa\u0bbe\u0ba4\u0bbf\u0b95\u0bcd\u0b95\u0baa\u0bcd\u0baa\u0b9f\u0bcd\u0b9f\u0ba9\u0bbe\u0bcd. \u0b95\u0bb0\u0bcb\u0ba9\u0bbe \u0baa\u0bbe\u0ba4\u0bbf\u0ba4\u0bcd\u0ba4\u0bc1 \u0b9a\u0bbf\u0b95\u0bbf\u0b9a\u0bcd\u0b9a\u0bc8 \u0baa\u0bc6\u0bb1\u0bcd\u0bb1\u0bc1 \u0bb5\u0ba8\u0bcd\u0ba4 1,133 \u0baa\u0bc7\u0bb0\u0bcd \u0b89\u0baf\u0bbf\u0bb0\u0bbf\u0bb4\u0ba8\u0bcd\u0ba4\u0ba9\u0bb0\u0bcd. <a href=\"https:\/\/www.dinamani.com\/india\/2020\/sep\/08\/caseload-rises-to-4280422-with-75809-fresh-cases-govt-3461158.html\" target=\"_blank\"><span style=\"color: rgb(255, 0, 0);\">\u0bb5\u0bbf\u0bb0\u0bbf\u0bb5\u0bbe\u0ba9 \u0b9a\u0bc6\u0baf\u0bcd\u0ba4\u0bbf\u0b95\u0bcd\u0b95\u0bc1..<\/span><\/a><\/p>","date":"2020-09-08 12:49:49","pin":"0","status":1},{"title":"\u0ba4\u0bae\u0bbf\u0bb4\u0b95\u0ba4\u0bcd\u0ba4\u0bbf\u0bb2\u0bcd 2,000 \u0b9a\u0bbf\u0bb1\u0bc1 \u0bae\u0bb0\u0bc1\u0ba4\u0bcd\u0ba4\u0bc1\u0bb5\u0bae\u0ba9\u0bc8\u0b95\u0bb3\u0bc8 \u0b8f\u0bb1\u0bcd\u0baa\u0b9f\u0bc1\u0ba4\u0bcd\u0ba4 \u0bae\u0bc1\u0b9f\u0bbf\u0bb5\u0bc1: \u0bae\u0bc1\u0ba4\u0bb2\u0bcd\u0bb5\u0bb0\u0bcd \u0baa\u0bb4\u0ba9\u0bbf\u0b9a\u0bbe\u0bae\u0bbf","content":"<p>&nbsp;\u0ba4\u0bae\u0bbf\u0bb4\u0b95\u0ba4\u0bcd\u0ba4\u0bbf\u0bb2\u0bcd \u0b85\u0ba4\u0bbf\u0b95\u0bb3\u0bb5\u0bbf\u0bb2\u0bcd \u0b95\u0bb0\u0bcb\u0ba9\u0bbe \u0baa\u0bb0\u0bbf\u0b9a\u0bcb\u0ba4\u0ba9\u0bc8\u0baf\u0bc8 \u0bae\u0bc7\u0bb1\u0bcd\u0b95\u0bca\u0bb3\u0bcd\u0bb3 \u0bb5\u0b9a\u0ba4\u0bbf\u0baf\u0bbe\u0b95, \u0b9a\u0bc1\u0bae\u0bbe\u0bb0\u0bcd 2 \u0b86\u0baf\u0bbf\u0bb0\u0bae\u0bcd \u0b9a\u0bbf\u0bb1\u0bc1 \u0bae\u0bb0\u0bc1\u0ba4\u0bcd\u0ba4\u0bc1\u0bb5\u0bae\u0ba9\u0bc8\u0b95\u0bb3\u0bc8 \u0b8f\u0bb1\u0bcd\u0baa\u0b9f\u0bc1\u0ba4\u0bcd\u0ba4 \u0bae\u0bc1\u0b9f\u0bbf\u0bb5\u0bc1 \u0b9a\u0bc6\u0baf\u0bcd\u0baf\u0baa\u0bcd\u0baa\u0b9f\u0bcd\u0b9f\u0bc1\u0bb3\u0bcd\u0bb3\u0ba4\u0bbe\u0b95 \u0ba4\u0bae\u0bbf\u0bb4\u0b95 \u0bae\u0bc1\u0ba4\u0bb2\u0bcd\u0bb5\u0bb0\u0bcd \u0b8e\u0b9f\u0baa\u0bcd\u0baa\u0bbe\u0b9f\u0bbf \u0b95\u0bc7. \u0baa\u0bb4\u0ba9\u0bbf\u0b9a\u0bbe\u0bae\u0bbf \u0ba4\u0bc6\u0bb0\u0bbf\u0bb5\u0bbf\u0ba4\u0bcd\u0ba4\u0bc1\u0bb3\u0bcd\u0bb3\u0bbe\u0bb0\u0bcd. <a href=\"https:\/\/www.dinamani.com\/tamilnadu\/2020\/sep\/08\/decision-to-set-up-2000-small-hospitals-in-tamil-nadu-chief-minister-palanisamy-3461175.html\" target=\"_blank\"><span style=\"color: rgb(255, 0, 0);\">\u0bb5\u0bbf\u0bb0\u0bbf\u0bb5\u0bbe\u0ba9 \u0b9a\u0bc6\u0baf\u0bcd\u0ba4\u0bbf\u0b95\u0bcd\u0b95\u0bc1..<\/span><\/a><\/p>","date":"2020-09-08 12:50:59","pin":"0","status":1},{"title":"\u0ba4\u0bae\u0bbf\u0bb4\u0b95\u0ba4\u0bcd\u0ba4\u0bbf\u0bb2\u0bcd \u0baa\u0bc1\u0ba4\u0bbf\u0ba4\u0bbe\u0b95 5,684 \u0baa\u0bc7\u0bb0\u0bc1\u0b95\u0bcd\u0b95\u0bc1 \u0b95\u0bb0\u0bcb\u0ba9\u0bbe: \u0bae\u0bc7\u0bb2\u0bc1\u0bae\u0bcd 87 \u0baa\u0bc7\u0bb0\u0bcd \u0baa\u0bb2\u0bbf","content":"<p><span style=\"color: rgb(51, 51, 51); font-family: &quot;Noto Sans Tamil&quot;, sans-serif; font-size: 14px; text-align: justify;\">\u0ba4\u0bae\u0bbf\u0bb4\u0b95\u0ba4\u0bcd\u0ba4\u0bbf\u0bb2\u0bcd \u0baa\u0bc1\u0ba4\u0bbf\u0ba4\u0bbe\u0b95 5,684 \u0baa\u0bc7\u0bb0\u0bc1\u0b95\u0bcd\u0b95\u0bc1 \u0b95\u0bb0\u0bcb\u0ba9\u0bbe \u0bb5\u0bc8\u0bb0\u0bb8\u0bcd \u0ba8\u0bcb\u0baf\u0bcd\u0ba4\u0bcd \u0ba4\u0bca\u0bb1\u0bcd\u0bb1\u0bc1 \u0b87\u0bb0\u0bc1\u0baa\u0bcd\u0baa\u0ba4\u0bc1 \u0b87\u0ba9\u0bcd\u0bb1\u0bc1 (\u0b9a\u0bc6\u0bb5\u0bcd\u0bb5\u0bbe\u0baf\u0bcd\u0b95\u0bcd\u0b95\u0bbf\u0bb4\u0bae\u0bc8) \u0b89\u0bb1\u0bc1\u0ba4\u0bbf \u0b9a\u0bc6\u0baf\u0bcd\u0baf\u0baa\u0bcd\u0baa\u0b9f\u0bcd\u0b9f\u0bc1\u0bb3\u0bcd\u0bb3\u0ba4\u0bc1. <\/span><strong><span style=\"color: rgb(51, 51, 51); font-family: &quot;Noto Sans Tamil&quot;, sans-serif; font-size: 14px; text-align: justify;\"><a href=\"https:\/\/www.dinamani.com\/tamilnadu\/2020\/sep\/08\/corona-for-5684-newcomers-in-tamil-nadu-more-killed-3461232.html\" target=\"_blank\"><strong><span style=\"color: rgb(255, 0, 0);\"><u>\u0bb5\u0bbf\u0bb0\u0bbf\u0bb5\u0bbe\u0ba9 \u0b9a\u0bc6\u0baf\u0bcd\u0ba4\u0bbf\u0b95\u0bcd\u0b95\u0bc1..<\/u><\/span><\/strong><\/a><\/span><\/strong><\/p>","date":"2020-09-08 06:23:44","pin":"0","status":1},{"title":"\u0b9a\u0bc6\u0ba9\u0bcd\u0ba9\u0bc8\u0baf\u0bbf\u0bb2\u0bcd 988, \u0baa\u0bbf\u0bb1 \u0bae\u0bbe\u0bb5\u0b9f\u0bcd\u0b9f\u0b99\u0bcd\u0b95\u0bb3\u0bbf\u0bb2\u0bcd 4,696 \u0baa\u0bc7\u0bb0\u0bc1\u0b95\u0bcd\u0b95\u0bc1 \u0b95\u0bb0\u0bcb\u0ba9\u0bbe: \u0bae\u0bbe\u0bb5\u0b9f\u0bcd\u0b9f\u0bb5\u0bbe\u0bb0\u0bbf\u0baf\u0bbe\u0b95","content":"<p><span style=\"color: rgb(51, 51, 51); font-family: &quot;Noto Sans Tamil&quot;, sans-serif; font-size: 14px; text-align: justify;\">\u0b9a\u0bc6\u0ba9\u0bcd\u0ba9\u0bc8 \u0ba4\u0bb5\u0bbf\u0bb0\u0bcd\u0ba4\u0bcd\u0ba4\u0bc1 \u0baa\u0bbf\u0bb1 \u0bae\u0bbe\u0bb5\u0b9f\u0bcd\u0b9f\u0b99\u0bcd\u0b95\u0bb3\u0bbf\u0bb2\u0bcd \u0baa\u0bc1\u0ba4\u0bbf\u0ba4\u0bbe\u0b95 4,696 \u0baa\u0bc7\u0bb0\u0bc1\u0b95\u0bcd\u0b95\u0bc1 \u0b95\u0bb0\u0bcb\u0ba9\u0bbe \u0bb5\u0bc8\u0bb0\u0bb8\u0bcd \u0ba8\u0bcb\u0baf\u0bcd\u0ba4\u0bcd \u0ba4\u0bca\u0bb1\u0bcd\u0bb1\u0bc1 \u0b87\u0bb0\u0bc1\u0baa\u0bcd\u0baa\u0ba4\u0bc1 \u0b87\u0ba9\u0bcd\u0bb1\u0bc1 (\u0b9a\u0bc6\u0bb5\u0bcd\u0bb5\u0bbe\u0baf\u0bcd\u0b95\u0bcd\u0b95\u0bbf\u0bb4\u0bae\u0bc8) \u0b95\u0ba3\u0bcd\u0b9f\u0bb1\u0bbf\u0baf\u0baa\u0bcd\u0baa\u0b9f\u0bcd\u0b9f\u0bc1\u0bb3\u0bcd\u0bb3\u0ba4\u0bc1. <\/span><span style=\"color: rgb(255, 0, 0);\"><u><strong><span style=\"font-family: &quot;Noto Sans Tamil&quot;, sans-serif; font-size: 14px; text-align: justify;\"><a href=\"https:\/\/www.dinamani.com\/tamilnadu\/2020\/sep\/08\/988-new-cases-in-chennai-and-4696-new-cases-in-other-districts-districtwise-3461237.html\" target=\"_blank\"><span style=\"color: rgb(255, 0, 0);\">\u0bb5\u0bbf\u0bb0\u0bbf\u0bb5\u0bbe\u0ba9 \u0b9a\u0bc6\u0baf\u0bcd\u0ba4\u0bbf\u0b95\u0bcd\u0b95\u0bc1..<\/span><\/a><\/span><\/strong><\/u><\/span><\/p>\n<div>&nbsp;<\/div>","date":"2020-09-08 07:07:11","pin":"0","status":1},{"title":"\u0bae\u0b95\u0bbe\u0bb0\u0bbe\u0bb7\u0bcd\u0b9f\u0bbf\u0bb0\u0ba4\u0bcd\u0ba4\u0bbf\u0bb2\u0bcd \u0baa\u0bc1\u0ba4\u0bbf\u0ba4\u0bbe\u0b95 20,131 \u0baa\u0bc7\u0bb0\u0bc1\u0b95\u0bcd\u0b95\u0bc1 \u0b95\u0bb0\u0bcb\u0ba9\u0bbe: 380 \u0baa\u0bc7\u0bb0\u0bcd \u0baa\u0bb2\u0bbf","content":"<p><span style=\"color: rgb(51, 51, 51); font-family: &quot;Noto Sans Tamil&quot;, sans-serif; font-size: 14px; text-align: justify;\">\u0bae\u0b95\u0bbe\u0bb0\u0bbe\u0bb7\u0bcd\u0b9f\u0bbf\u0bb0\u0ba4\u0bcd\u0ba4\u0bbf\u0bb2\u0bcd \u0baa\u0bc1\u0ba4\u0bbf\u0ba4\u0bbe\u0b95 20,131 \u0baa\u0bc7\u0bb0\u0bc1\u0b95\u0bcd\u0b95\u0bc1 \u0b95\u0bb0\u0bcb\u0ba9\u0bbe \u0bb5\u0bc8\u0bb0\u0bb8\u0bcd \u0ba8\u0bcb\u0baf\u0bcd\u0ba4\u0bcd \u0ba4\u0bca\u0bb1\u0bcd\u0bb1\u0bc1 \u0b87\u0bb0\u0bc1\u0baa\u0bcd\u0baa\u0ba4\u0bc1 \u0b87\u0ba9\u0bcd\u0bb1\u0bc1 (\u0b9a\u0bc6\u0bb5\u0bcd\u0bb5\u0bbe\u0baf\u0bcd\u0b95\u0bcd\u0b95\u0bbf\u0bb4\u0bae\u0bc8) \u0b89\u0bb1\u0bc1\u0ba4\u0bbf \u0b9a\u0bc6\u0baf\u0bcd\u0baf\u0baa\u0bcd\u0baa\u0b9f\u0bcd\u0b9f\u0bc1\u0bb3\u0bcd\u0bb3\u0ba4\u0bc1. <\/span><u><strong><span style=\"color: rgb(51, 51, 51); font-family: &quot;Noto Sans Tamil&quot;, sans-serif; font-size: 14px; text-align: justify;\"><a href=\"https:\/\/www.dinamani.com\/india\/2020\/sep\/08\/maharashtra-records-20131-new-covid19-cases-380-deaths-today-3461256.html\" target=\"_blank\"><strong><span style=\"color: rgb(255, 0, 0);\">\u0bb5\u0bbf\u0bb0\u0bbf\u0bb5\u0bbe\u0ba9 \u0b9a\u0bc6\u0baf\u0bcd\u0ba4\u0bbf\u0b95\u0bcd\u0b95\u0bc1..<\/span><\/strong><\/a><\/span><\/strong><\/u><\/p>","date":"2020-09-08 09:47:57","pin":"0","status":1},{"title":"\u0b95\u0bc7\u0bb0\u0bb3\u0ba4\u0bcd\u0ba4\u0bbf\u0bb2\u0bcd 1 \u0bb2\u0b9f\u0bcd\u0b9a\u0ba4\u0bcd\u0ba4\u0bc8 \u0ba8\u0bc6\u0bb0\u0bc1\u0b99\u0bcd\u0b95\u0bc1\u0bae\u0bcd \u0b95\u0bb0\u0bcb\u0ba9\u0bbe \u0baa\u0bbe\u0ba4\u0bbf\u0baa\u0bcd\u0baa\u0bc1","content":"<p>&nbsp;<span style=\"color: rgb(51, 51, 51); font-family: &quot;Noto Sans Tamil&quot;, sans-serif; font-size: 14px; text-align: justify;\">\u0b95\u0bc7\u0bb0\u0bb3\u0ba4\u0bcd\u0ba4\u0bbf\u0bb2\u0bcd \u0b87\u0ba9\u0bcd\u0bb1\u0bc1 (\u0b9a\u0bc6\u0bb5\u0bcd\u0bb5\u0bbe\u0baf\u0bcd\u0b95\u0bcd\u0b95\u0bbf\u0bb4\u0bae\u0bc8) \u0baa\u0bc1\u0ba4\u0bbf\u0ba4\u0bbe\u0b95 3,026 \u0baa\u0bc7\u0bb0\u0bc1\u0b95\u0bcd\u0b95\u0bc1 \u0b95\u0bb0\u0bcb\u0ba9\u0bbe \u0bb5\u0bc8\u0bb0\u0bb8\u0bcd \u0ba8\u0bcb\u0baf\u0bcd\u0ba4\u0bcd \u0ba4\u0bca\u0bb1\u0bcd\u0bb1\u0bc1 \u0b87\u0bb0\u0bc1\u0baa\u0bcd\u0baa\u0ba4\u0bc1 \u0b89\u0bb1\u0bc1\u0ba4\u0bbf \u0b9a\u0bc6\u0baf\u0bcd\u0baf\u0baa\u0bcd\u0baa\u0b9f\u0bcd\u0b9f\u0bc1\u0bb3\u0bcd\u0bb3\u0ba4\u0bc1. \u0b87\u0ba4\u0ba9\u0bcd\u0bae\u0bc2\u0bb2\u0bae\u0bcd, \u0bae\u0bbe\u0ba8\u0bbf\u0bb2\u0ba4\u0bcd\u0ba4\u0bbf\u0ba9\u0bcd \u0bae\u0bca\u0ba4\u0bcd\u0ba4 \u0b95\u0bb0\u0bcb\u0ba9\u0bbe \u0baa\u0bbe\u0ba4\u0bbf\u0baa\u0bcd\u0baa\u0bc1 1 \u0bb2\u0b9f\u0bcd\u0b9a\u0ba4\u0bcd\u0ba4\u0bc8 \u0ba8\u0bc6\u0bb0\u0bc1\u0b99\u0bcd\u0b95\u0bbf\u0baf\u0bc1\u0bb3\u0bcd\u0bb3\u0ba4\u0bc1.<\/span><\/p>\n<div>&nbsp;<\/div>","date":"2020-09-08 09:48:27","pin":"0","status":1},{"title":"\u0b9a\u0bc6\u0ba9\u0bcd\u0ba9\u0bc8\u0baf\u0bbf\u0bb2\u0bcd 11 \u0b86\u0baf\u0bbf\u0bb0\u0bae\u0bcd \u0baa\u0bc7\u0bb0\u0bcd \u0b95\u0bb0\u0bcb\u0ba9\u0bbe \u0b9a\u0bbf\u0b95\u0bbf\u0b9a\u0bcd\u0b9a\u0bc8\u0baf\u0bbf\u0bb2\u0bcd","content":"<p>&nbsp;\u0b9a\u0bc6\u0ba9\u0bcd\u0ba9\u0bc8\u0baf\u0bbf\u0bb2\u0bcd \u0b95\u0bb0\u0bcb\u0ba9\u0bbe \u0baa\u0bbe\u0ba4\u0bbf\u0ba4\u0bcd\u0ba4\u0bc1 \u0b95\u0bc1\u0ba3\u0bae\u0b9f\u0bc8\u0ba8\u0bcd\u0ba4\u0bcb\u0bb0\u0bcd \u0bb5\u0bbf\u0b95\u0bbf\u0ba4\u0bae\u0bcd 90% \u0b86\u0b95 \u0b89\u0baf\u0bb0\u0bcd\u0ba8\u0bcd\u0ba4\u0bc1\u0bb3\u0bcd\u0bb3\u0ba4\u0bc1. \u0b87\u0ba9\u0bcd\u0bb1\u0bc1 \u0b95\u0bbe\u0bb2\u0bc8 \u0ba8\u0bbf\u0bb2\u0bb5\u0bb0\u0baa\u0bcd\u0baa\u0b9f\u0bbf 11,029 \u0baa\u0bc7\u0bb0\u0bcd (8%) \u0b9a\u0bbf\u0b95\u0bbf\u0b9a\u0bcd\u0b9a\u0bc8 \u0baa\u0bc6\u0bb1\u0bcd\u0bb1\u0bc1 \u0bb5\u0bb0\u0bc1\u0b95\u0bbf\u0bb1\u0bbe\u0bb0\u0bcd\u0b95\u0bb3\u0bcd.&nbsp; <a href=\"https:\/\/www.dinamani.com\/tamilnadu\/2020\/sep\/09\/11-thousand-people-in-corona-treatment-in-chennai-3461849.html\" target=\"_blank\"><span style=\"color: rgb(255, 0, 0);\">\u0bb5\u0bbf\u0bb0\u0bbf\u0bb5\u0bbe\u0ba9 \u0b9a\u0bc6\u0baf\u0bcd\u0ba4\u0bbf\u0b95\u0bcd\u0b95\u0bc1..<\/span><\/a><\/p>","date":"2020-09-09 04:43:49","pin":"0","status":1},{"title":"'\u0baa\u0bbe\u0b9f\u0bc1\u0bb5\u0ba4\u0bbe\u0bb2\u0bcd \u0b95\u0bb0\u0bcb\u0ba9\u0bbe \u0ba4\u0bca\u0bb1\u0bcd\u0bb1\u0bc1 \u0b85\u0ba4\u0bbf\u0b95\u0bae\u0bcd \u0baa\u0bb0\u0bb5\u0bc1\u0bae\u0bcd'","content":"<p>&nbsp;\u0baa\u0bbe\u0b9f\u0bc1\u0bb5\u0ba4\u0bbe\u0bb2\u0bcd \u0b95\u0bb0\u0bcb\u0ba9\u0bbe \u0ba4\u0bca\u0bb1\u0bcd\u0bb1\u0bc1 \u0b85\u0ba4\u0bbf\u0b95\u0bae\u0bcd \u0baa\u0bb0\u0bb5\u0bc1\u0bae\u0bcd \u0b8e\u0ba9\u0bcd\u0bb1\u0bc1\u0bae\u0bcd, \u0b95\u0bb0\u0bcb\u0ba9\u0bbe\u0bb5\u0bc8\u0b95\u0bcd \u0b95\u0b9f\u0bcd\u0b9f\u0bc1\u0baa\u0bcd\u0baa\u0b9f\u0bc1\u0ba4\u0bcd\u0ba4 \u0baa\u0bbe\u0b9f\u0bc1\u0bb5\u0ba4\u0bc8\u0ba4\u0bcd \u0ba4\u0bb5\u0bbf\u0bb0\u0bcd\u0b95\u0bcd\u0b95 \u0bb5\u0bc7\u0ba3\u0bcd\u0b9f\u0bc1\u0bae\u0bcd \u0b8e\u0ba9\u0bcd\u0bb1\u0bc1\u0bae\u0bcd \u0b92\u0bb0\u0bc1 \u0b86\u0bb0\u0bbe\u0baf\u0bcd\u0b9a\u0bcd\u0b9a\u0bbf \u0b95\u0bc2\u0bb1\u0bc1\u0b95\u0bbf\u0bb1\u0ba4\u0bc1. <a href=\"https:\/\/www.dinamani.com\/world\/2020\/sep\/09\/avoid-singing-to-cut-the-spread-of-covid-19-infection-study-3461892.html\" target=\"_blank\"><span style=\"color: rgb(255, 0, 0);\">\u0bb5\u0bbf\u0bb0\u0bbf\u0bb5\u0bbe\u0ba9 \u0b9a\u0bc6\u0baf\u0bcd\u0ba4\u0bbf\u0b95\u0bcd\u0b95\u0bc1..<\/span><\/a><\/p>","date":"2020-09-09 04:48:01","pin":"0","status":1},{"title":"\u0ba4\u0bae\u0bbf\u0bb4\u0b95\u0ba4\u0bcd\u0ba4\u0bbf\u0bb2\u0bcd \u0b95\u0bb0\u0bcb\u0ba9\u0bbe\u0bb5\u0bbf\u0bb2\u0bcd \u0b87\u0bb0\u0bc1\u0ba8\u0bcd\u0ba4\u0bc1 \u0ba8\u0bb2\u0bae\u0b9f\u0bc8\u0bb5\u0bcb\u0bb0\u0bcd \u0bb5\u0bbf\u0b95\u0bbf\u0ba4\u0bae\u0bcd \u0b85\u0ba4\u0bbf\u0b95\u0bb0\u0bbf\u0baa\u0bcd\u0baa\u0bc1: \u0bae\u0bc1\u0ba4\u0bb2\u0bcd\u0bb5\u0bb0\u0bcd \u0baa\u0bb4\u0ba9\u0bbf\u0b9a\u0bbe\u0bae\u0bbf","content":"<p>&nbsp;\u0ba4\u0bae\u0bbf\u0bb4\u0b95\u0ba4\u0bcd\u0ba4\u0bbf\u0bb2\u0bcd \u0b95\u0bb0\u0bcb\u0ba9\u0bbe\u0bb5\u0bbf\u0bb2\u0bcd \u0b87\u0bb0\u0bc1\u0ba8\u0bcd\u0ba4\u0bc1 \u0ba8\u0bb2\u0bae\u0b9f\u0bc8\u0bb5\u0bcb\u0bb0\u0bcd \u0bb5\u0bbf\u0b95\u0bbf\u0ba4\u0bae\u0bcd \u0b85\u0ba4\u0bbf\u0b95\u0bb0\u0bbf\u0ba4\u0bcd\u0ba4\u0bc1\u0bb3\u0bcd\u0bb3\u0ba4\u0bbe\u0b95\u0bb5\u0bc1\u0bae\u0bcd, \u0b95\u0bb0\u0bcb\u0ba9\u0bbe\u0bb5\u0bc1\u0b95\u0bcd\u0b95\u0bc1 \u0baa\u0bb2\u0bbf\u0baf\u0bbe\u0bb5\u0bcb\u0bb0\u0bcd \u0bb5\u0bbf\u0b95\u0bbf\u0ba4\u0bae\u0bcd \u0b95\u0bc1\u0bb1\u0bc8\u0bb5\u0bbe\u0b95 \u0b87\u0bb0\u0bc1\u0baa\u0bcd\u0baa\u0ba4\u0bbe\u0b95\u0bb5\u0bc1\u0bae\u0bcd \u0bae\u0bc1\u0ba4\u0bb2\u0bcd\u0bb5\u0bb0\u0bcd \u0baa\u0bb4\u0ba9\u0bbf\u0b9a\u0bbe\u0bae\u0bbf \u0ba4\u0bc6\u0bb0\u0bbf\u0bb5\u0bbf\u0ba4\u0bcd\u0ba4\u0bc1\u0bb3\u0bcd\u0bb3\u0bbe\u0bb0\u0bcd. <a href=\"https:\/\/www.dinamani.com\/tamilnadu\/2020\/sep\/09\/increase-in-the-rate-of-recovery-from-corona-in-tamil-nadu-chief-minister-palanisamy-3461860.html\" target=\"_blank\"><span style=\"color: rgb(255, 0, 0);\">\u0bb5\u0bbf\u0bb0\u0bbf\u0bb5\u0bbe\u0ba9 \u0b9a\u0bc6\u0baf\u0bcd\u0ba4\u0bbf\u0b95\u0bcd\u0b95\u0bc1..<\/span><\/a><\/p>","date":"2020-09-09 04:48:36","pin":"0","status":1},{"title":"\u0bae\u0bcb\u0b9a\u0bae\u0bbe\u0ba9 \u0baa\u0b95\u0bcd\u0b95\u0bb5\u0bbf\u0bb3\u0bc8\u0bb5\u0bc1: \u0b86\u0b95\u0bcd\u0bb8\u0bcd\u0b83\u0baa\u0bcb\u0bb0\u0bcd\u0b9f\u0bc1 \u0baa\u0bb2\u0bcd\u0b95\u0bb2\u0bc8\u0baf\u0bbf\u0ba9\u0bcd \u0b95\u0bb0\u0bcb\u0ba9\u0bbe \u0ba4\u0b9f\u0bc1\u0baa\u0bcd\u0baa\u0bc2\u0b9a\u0bbf \u0b9a\u0bcb\u0ba4\u0ba9\u0bc8 \u0ba8\u0bbf\u0bb1\u0bc1\u0ba4\u0bcd\u0ba4\u0bae\u0bcd","content":"<p>&nbsp;\u0b86\u0bb8\u0bcd\u0b9f\u0bcd\u0bb0\u0bbe\u0b9c\u0bc6\u0ba9\u0bc6\u0b95\u0bbe \u0b95\u0ba3\u0bcd\u0b9f\u0bc1\u0baa\u0bbf\u0b9f\u0bbf\u0ba4\u0bcd\u0ba4 \u0b95\u0bb0\u0bcb\u0ba9\u0bbe \u0ba4\u0b9f\u0bc1\u0baa\u0bcd\u0baa\u0bc1 \u0bae\u0bb0\u0bc1\u0ba8\u0bcd\u0ba4\u0bc1 \u0b9a\u0bc6\u0bb2\u0bc1\u0ba4\u0bcd\u0ba4\u0baa\u0bcd\u0baa\u0b9f\u0bcd\u0b9f \u0ba4\u0ba9\u0bcd\u0ba9\u0bbe\u0bb0\u0bcd\u0bb5\u0bb2\u0bb0\u0bc1\u0b95\u0bcd\u0b95\u0bc1 \u0bb5\u0bbf\u0bb3\u0b95\u0bcd\u0b95\u0bae\u0bc1\u0b9f\u0bbf\u0baf\u0bbe\u0ba4 \u0b89\u0b9f\u0bb2\u0bcd\u0ba8\u0bb2\u0baa\u0bcd \u0baa\u0bbe\u0ba4\u0bbf\u0baa\u0bcd\u0baa\u0bc1 \u0b8f\u0bb1\u0bcd\u0baa\u0b9f\u0bcd\u0b9f\u0ba4\u0bbe\u0bb2\u0bcd, \u0ba4\u0b9f\u0bc1\u0baa\u0bcd\u0baa\u0bc1 \u0bae\u0bb0\u0bc1\u0ba8\u0bcd\u0ba4\u0bc1 \u0b9a\u0bcb\u0ba4\u0ba9\u0bc8 \u0ba4\u0bb1\u0bcd\u0b95\u0bbe\u0bb2\u0bbf\u0b95\u0bae\u0bbe\u0b95 \u0ba8\u0bbf\u0bb1\u0bc1\u0ba4\u0bcd\u0ba4\u0baa\u0bcd\u0baa\u0b9f\u0bcd\u0b9f\u0bc1\u0bb3\u0bcd\u0bb3\u0ba4\u0bc1. <a href=\"https:\/\/www.dinamani.com\/world\/2020\/sep\/09\/unexplained-illness-oxford-university-corona-vaccine-test-pauses-3461856.html\" target=\"_blank\"><span style=\"color: rgb(255, 0, 0);\">\u0bb5\u0bbf\u0bb0\u0bbf\u0bb5\u0bbe\u0ba9 \u0b9a\u0bc6\u0baf\u0bcd\u0ba4\u0bbf\u0b95\u0bcd\u0b95\u0bc1..<\/span><\/a><\/p>","date":"2020-09-09 04:49:15","pin":"0","status":1},{"title":"\u0bae\u0b95\u0bbe\u0bb0\u0bbe\u0bb7\u0bcd\u0b9f\u0bbf\u0bb0\u0ba4\u0bcd\u0ba4\u0bbf\u0bb2\u0bcd \u0baa\u0bc1\u0ba4\u0bbf\u0ba4\u0bbe\u0b95 553 \u0b95\u0bbe\u0bb5\u0bb2\u0bb0\u0bcd\u0b95\u0bb3\u0bc1\u0b95\u0bcd\u0b95\u0bc1 \u0b95\u0bb0\u0bcb\u0ba9\u0bbe: \u0bae\u0bc7\u0bb2\u0bc1\u0bae\u0bcd  3 \u0baa\u0bc7\u0bb0\u0bcd \u0baa\u0bb2\u0bbf","content":"<p>&nbsp;\u0bae\u0b95\u0bbe\u0bb0\u0bbe\u0bb7\u0bcd\u0b9f\u0bbf\u0bb0\u0ba4\u0bcd\u0ba4\u0bbf\u0bb2\u0bcd \u0b95\u0b9f\u0ba8\u0bcd\u0ba4 24 \u0bae\u0ba3\u0bbf\u0ba8\u0bc7\u0bb0\u0ba4\u0bcd\u0ba4\u0bbf\u0bb2\u0bcd \u0baa\u0bc1\u0ba4\u0bbf\u0ba4\u0bbe\u0b95 553 \u0b95\u0bbe\u0bb5\u0bb2\u0bb0\u0bcd\u0b95\u0bb3\u0bc1\u0b95\u0bcd\u0b95\u0bc1 \u0b95\u0bb0\u0bcb\u0ba9\u0bbe \u0bb5\u0bc8\u0bb0\u0bb8\u0bcd \u0ba4\u0bca\u0bb1\u0bcd\u0bb1\u0bc1 \u0b89\u0bb1\u0bc1\u0ba4\u0bbf \u0b9a\u0bc6\u0baf\u0bcd\u0baf\u0baa\u0bcd\u0baa\u0b9f\u0bcd\u0b9f\u0bc1\u0bb3\u0bcd\u0bb3\u0ba4\u0bc1. \u0bae\u0bc7\u0bb2\u0bc1\u0bae\u0bcd 3 \u0b95\u0bbe\u0bb5\u0bb2\u0bb0\u0bcd\u0b95\u0bb3\u0bcd \u0b89\u0baf\u0bbf\u0bb0\u0bbf\u0bb4\u0ba8\u0bcd\u0ba4\u0ba9\u0bb0\u0bcd.<\/p>\n<div><a href=\"https:\/\/www.dinamani.com\/india\/2020\/sep\/09\/533-more-maharashtra-police-personnel-tested-covid19-positive-while-3-died-3461880.html\" target=\"_blank\"><span style=\"color: rgb(255, 0, 0);\">\u0bb5\u0bbf\u0bb0\u0bbf\u0bb5\u0bbe\u0ba9 \u0b9a\u0bc6\u0baf\u0bcd\u0ba4\u0bbf\u0b95\u0bcd\u0b95\u0bc1...<\/span><\/a><\/div>","date":"2020-09-09 04:51:05","pin":"0","status":1},{"title":"\u0bb0\u0bb7\u0bbf\u0baf\u0bbe\u0bb5\u0bbf\u0bb2\u0bcd \u0b95\u0bb0\u0bcb\u0ba9\u0bbe \u0baa\u0bb2\u0bbf 18 \u0b86\u0baf\u0bbf\u0bb0\u0ba4\u0bcd\u0ba4\u0bc8\u0ba4\u0bcd \u0ba4\u0bbe\u0ba3\u0bcd\u0b9f\u0bbf\u0baf\u0ba4\u0bc1!","content":"<p><span style=\"color: rgb(51, 51, 51); font-family: &quot;Noto Sans Tamil&quot;, sans-serif; font-size: 14px; text-align: justify;\">\u0bb0\u0bb7\u0bbf\u0baf\u0bbe\u0bb5\u0bbf\u0bb2\u0bcd \u0baa\u0bc1\u0ba4\u0bbf\u0ba4\u0bbe\u0b95 5,218 \u0baa\u0bc7\u0bb0\u0bc1\u0b95\u0bcd\u0b95\u0bc1 \u0b95\u0bb0\u0bcb\u0ba9\u0bbe \u0ba4\u0bca\u0bb1\u0bcd\u0bb1\u0bc1 \u0b89\u0bb1\u0bc1\u0ba4\u0bbf\u0baf\u0bbe\u0b95\u0bbf\u0baf\u0bc1\u0bb3\u0bcd\u0bb3\u0ba4\u0bc1. \u0bae\u0bc7\u0bb2\u0bc1\u0bae\u0bcd 142 \u0baa\u0bc7\u0bb0\u0bcd \u0baa\u0bb2\u0bbf\u0baf\u0bbe\u0b95\u0bbf\u0baf\u0bc1\u0bb3\u0bcd\u0bb3\u0ba9\u0bb0\u0bcd. <a href=\"https:\/\/www.dinamani.com\/world\/2020\/sep\/09\/russias-corona-virus-death-toll-crosses-18k-3461902.html\"><span style=\"color: rgb(255, 0, 0);\">\u0bb5\u0bbf\u0bb0\u0bbf\u0bb5\u0bbe\u0ba9 \u0b9a\u0bc6\u0baf\u0bcd\u0ba4\u0bbf\u0b95\u0bcd\u0b95\u0bc1...<\/span><\/a><\/span><\/p>\n<div>&nbsp;<\/div>","date":"2020-09-09 05:21:42","pin":"0","status":1},{"title":"\u0b86\u0ba8\u0bcd\u0ba4\u0bbf\u0bb0\u0ba4\u0bcd\u0ba4\u0bbf\u0bb2\u0bcd 10,418, \u0b95\u0bb0\u0bcd\u0ba8\u0bbe\u0b9f\u0b95\u0ba4\u0bcd\u0ba4\u0bbf\u0bb2\u0bcd 9,540 \u0baa\u0bc7\u0bb0\u0bc1\u0b95\u0bcd\u0b95\u0bc1 \u0b95\u0bb0\u0bcb\u0ba9\u0bbe","content":"<p><span style=\"color: rgb(51, 51, 51); font-family: &quot;Noto Sans Tamil&quot;, sans-serif; font-size: 14px; text-align: justify;\">\u0b86\u0ba8\u0bcd\u0ba4\u0bbf\u0bb0\u0baa\u0bcd \u0baa\u0bbf\u0bb0\u0ba4\u0bc7\u0b9a\u0bae\u0bcd, \u0b95\u0bb0\u0bcd\u0ba8\u0bbe\u0b9f\u0b95\u0bae\u0bcd \u0bae\u0bbe\u0ba8\u0bbf\u0bb2\u0b99\u0bcd\u0b95\u0bb3\u0bbf\u0bb2\u0bcd \u0b95\u0bb0\u0bcb\u0ba9\u0bbe \u0ba4\u0bca\u0bb1\u0bcd\u0bb1\u0bbe\u0bb2\u0bcd \u0baa\u0bc1\u0ba4\u0bbf\u0ba4\u0bbe\u0b95 \u0baa\u0bbe\u0ba4\u0bbf\u0b95\u0bcd\u0b95\u0baa\u0bcd\u0baa\u0b9f\u0bcd\u0b9f\u0bcb\u0bb0\u0bcd, \u0baa\u0bb2\u0bbf\u0baf\u0bbe\u0ba9\u0bcb\u0bb0\u0bcd, \u0b95\u0bc1\u0ba3\u0bae\u0b9f\u0bc8\u0ba8\u0bcd\u0ba4\u0bcb\u0bb0\u0bcd \u0baa\u0bb1\u0bcd\u0bb1\u0bbf\u0baf \u0ba4\u0bb0\u0bb5\u0bc1\u0b95\u0bb3\u0bcd \u0b85\u0b9f\u0b99\u0bcd\u0b95\u0bbf\u0baf \u0b9a\u0bc6\u0baf\u0bcd\u0ba4\u0bbf\u0b95\u0bcd \u0b95\u0bc1\u0bb1\u0bbf\u0baa\u0bcd\u0baa\u0bc1\u0b95\u0bb3\u0bcd \u0bb5\u0bc6\u0bb3\u0bbf\u0baf\u0bbe\u0b95\u0bbf\u0baf\u0bc1\u0bb3\u0bcd\u0bb3\u0ba9. <\/span><strong><span style=\"color: rgb(51, 51, 51); font-family: &quot;Noto Sans Tamil&quot;, sans-serif; font-size: 14px; text-align: justify;\"><a href=\"https:\/\/www.dinamani.com\/india\/2020\/sep\/09\/10418-new-cases-reported-in-andhra-pradesh-and-9540-in-karnataka-3461931.html\" target=\"_blank\"><span style=\"color: rgb(255, 0, 0);\"><u><strong>\u0bb5\u0bbf\u0bb0\u0bbf\u0bb5\u0bbe\u0ba9 \u0b9a\u0bc6\u0baf\u0bcd\u0ba4\u0bbf\u0b95\u0bcd\u0b95\u0bc1..<\/strong><\/u><\/span><\/a><\/span><\/strong><\/p>\n<div>&nbsp;<\/div>","date":"2020-09-09 08:17:52","pin":"0","status":1},{"title":"\u0ba4\u0bae\u0bbf\u0bb4\u0b95\u0ba4\u0bcd\u0ba4\u0bbf\u0bb2\u0bcd \u0b87\u0ba9\u0bcd\u0bb1\u0bc1 5,584 \u0baa\u0bc7\u0bb0\u0bc1\u0b95\u0bcd\u0b95\u0bc1 \u0b95\u0bb0\u0bcb\u0ba9\u0bbe","content":"<p><span style=\"color: rgb(51, 51, 51); font-family: &quot;Noto Sans Tamil&quot;, sans-serif; font-size: 14px; text-align: justify;\">\u0ba4\u0bae\u0bbf\u0bb4\u0b95\u0ba4\u0bcd\u0ba4\u0bbf\u0bb2\u0bcd \u0b87\u0ba9\u0bcd\u0bb1\u0bc1 (\u0baa\u0bc1\u0ba4\u0ba9\u0bcd\u0b95\u0bbf\u0bb4\u0bae\u0bc8) \u0baa\u0bc1\u0ba4\u0bbf\u0ba4\u0bbe\u0b95 5,584 \u0baa\u0bc7\u0bb0\u0bc1\u0b95\u0bcd\u0b95\u0bc1 \u0b95\u0bb0\u0bcb\u0ba9\u0bbe \u0ba4\u0bca\u0bb1\u0bcd\u0bb1\u0bc1 \u0b87\u0bb0\u0bc1\u0baa\u0bcd\u0baa\u0ba4\u0bc1 \u0b95\u0ba3\u0bcd\u0b9f\u0bb1\u0bbf\u0baf\u0baa\u0bcd\u0baa\u0b9f\u0bcd\u0b9f\u0bc1\u0bb3\u0bcd\u0bb3\u0ba4\u0bc1. <\/span><span style=\"color: rgb(255, 0, 0);\"><u><strong><span style=\"font-family: &quot;Noto Sans Tamil&quot;, sans-serif; font-size: 14px; text-align: justify;\"><a href=\"https:\/\/www.dinamani.com\/tamilnadu\/2020\/sep\/09\/5584-new-positive-cases-reported-in-tamil-nadu-today-3461934.html\" target=\"_blank\"><u><strong><span style=\"color: rgb(255, 0, 0);\">\u0bb5\u0bbf\u0bb0\u0bbf\u0bb5\u0bbe\u0ba9 \u0b9a\u0bc6\u0baf\u0bcd\u0ba4\u0bbf\u0b95\u0bcd\u0b95\u0bc1..<\/span><\/strong><\/u><\/a><\/span><\/strong><\/u><\/span><\/p>\n<div>&nbsp;<\/div>","date":"2020-09-09 09:16:36","pin":"0","status":1},{"title":"\u0b9a\u0bc6\u0ba9\u0bcd\u0ba9\u0bc8\u0baf\u0bbf\u0bb2\u0bcd \u0bae\u0b9f\u0bcd\u0b9f\u0bc1\u0bae\u0bcd 993 \u0baa\u0bc7\u0bb0\u0bc1\u0b95\u0bcd\u0b95\u0bc1 \u0b95\u0bb0\u0bcb\u0ba9\u0bbe: \u0bae\u0bbe\u0bb5\u0b9f\u0bcd\u0b9f\u0bb5\u0bbe\u0bb0\u0bbf\u0baf\u0bbe\u0b95","content":"<p><span style=\"color: rgb(51, 51, 51); font-family: &quot;Noto Sans Tamil&quot;, sans-serif; font-size: 14px; text-align: justify;\">\u0b9a\u0bc6\u0ba9\u0bcd\u0ba9\u0bc8 \u0ba4\u0bb5\u0bbf\u0bb0\u0bcd\u0ba4\u0bcd\u0ba4\u0bc1 \u0ba4\u0bae\u0bbf\u0bb4\u0b95\u0ba4\u0bcd\u0ba4\u0bbf\u0ba9\u0bcd \u0baa\u0bbf\u0bb1 \u0bae\u0bbe\u0bb5\u0b9f\u0bcd\u0b9f\u0b99\u0bcd\u0b95\u0bb3\u0bbf\u0bb2\u0bcd \u0baa\u0bc1\u0ba4\u0bbf\u0ba4\u0bbe\u0b95 4,591 \u0baa\u0bc7\u0bb0\u0bc1\u0b95\u0bcd\u0b95\u0bc1 \u0b95\u0bb0\u0bcb\u0ba9\u0bbe \u0bb5\u0bc8\u0bb0\u0bb8\u0bcd \u0ba8\u0bcb\u0baf\u0bcd\u0ba4\u0bcd \u0ba4\u0bca\u0bb1\u0bcd\u0bb1\u0bc1 \u0b87\u0bb0\u0bc1\u0baa\u0bcd\u0baa\u0ba4\u0bc1 \u0b87\u0ba9\u0bcd\u0bb1\u0bc1 (\u0baa\u0bc1\u0ba4\u0ba9\u0bcd\u0b95\u0bbf\u0bb4\u0bae\u0bc8) \u0b89\u0bb1\u0bc1\u0ba4\u0bbf \u0b9a\u0bc6\u0baf\u0bcd\u0baf\u0baa\u0bcd\u0baa\u0b9f\u0bcd\u0b9f\u0bc1\u0bb3\u0bcd\u0bb3\u0ba4\u0bc1. <\/span><span style=\"color: rgb(255, 0, 0);\"><u><strong><span style=\"font-family: &quot;Noto Sans Tamil&quot;, sans-serif; font-size: 14px; text-align: justify;\"><a href=\"https:\/\/www.dinamani.com\/tamilnadu\/2020\/sep\/09\/993-cases-in-chennai-alone-district-wise-3461938.html\" target=\"_blank\"><span style=\"color: rgb(255, 0, 0);\">\u0bb5\u0bbf\u0bb0\u0bbf\u0bb5\u0bbe\u0ba9 \u0b9a\u0bc6\u0baf\u0bcd\u0ba4\u0bbf\u0b95\u0bcd\u0b95\u0bc1..<\/span><\/a><\/span><\/strong><\/u><\/span><\/p>\n<div>&nbsp;<\/div>","date":"2020-09-09 09:44:37","pin":"0","status":1},{"title":"\u0b9a\u0bc6\u0ba9\u0bcd\u0ba9\u0bc8\u0baf\u0bbf\u0bb2\u0bcd 10-\u0b95\u0bcd\u0b95\u0bc1\u0bae\u0bcd \u0bae\u0bc7\u0bb1\u0bcd\u0baa\u0b9f\u0bcd\u0b9f\u0bcb\u0bb0\u0bc1\u0b95\u0bcd\u0b95\u0bc1 \u0bae\u0bc0\u0ba3\u0bcd\u0b9f\u0bc1\u0bae\u0bcd \u0b95\u0bb0\u0bcb\u0ba9\u0bbe \u0ba4\u0bca\u0bb1\u0bcd\u0bb1\u0bc1","content":"<p>&nbsp;\u0b9a\u0bc6\u0ba9\u0bcd\u0ba9\u0bc8\u0baf\u0bbf\u0bb2\u0bcd \u0baa\u0ba4\u0bcd\u0ba4\u0bc1\u0b95\u0bcd\u0b95\u0bc1\u0bae\u0bcd \u0bae\u0bc7\u0bb1\u0bcd\u0baa\u0b9f\u0bcd\u0b9f\u0bcb\u0bb0\u0bc1\u0b95\u0bcd\u0b95\u0bc1 \u0b87\u0bb0\u0ba3\u0bcd\u0b9f\u0bbe\u0bb5\u0ba4\u0bc1 \u0bae\u0bc1\u0bb1\u0bc8\u0baf\u0bbe\u0b95 \u0b95\u0bb0\u0bcb\u0ba9\u0bbe \u0ba4\u0bca\u0bb1\u0bcd\u0bb1\u0bc1 \u0b8f\u0bb1\u0bcd\u0baa\u0b9f\u0bcd\u0b9f\u0bc1\u0bb3\u0bcd\u0bb3\u0ba4\u0bbe\u0b95\u0b95\u0bcd \u0b95\u0bc2\u0bb1\u0baa\u0bcd\u0baa\u0b9f\u0bc1\u0b95\u0bbf\u0bb1\u0ba4\u0bc1.<a href=\"https:\/\/www.dinamani.com\/all-editions\/edition-chennai\/chennai\/2020\/sep\/10\/more-than-10-recurrent-corona-infections-in-chennai-3462459.html\" target=\"_blank\"><span style=\"color: rgb(255, 0, 0);\"> \u0bb5\u0bbf\u0bb0\u0bbf\u0bb5\u0bbe\u0ba9 \u0b9a\u0bc6\u0baf\u0bcd\u0ba4\u0bbf\u0b95\u0bcd\u0b95\u0bc1..<\/span><\/a><\/p>","date":"2020-09-10 03:03:14","pin":"0","status":1},{"title":"\u0baa\u0bc6\u0b99\u0bcd\u0b95\u0bb3\u0bc2\u0bb0\u0bc1: \u0b86\u0bae\u0bcd\u0baa\u0bc1\u0bb2\u0ba9\u0bcd\u0bb8\u0bbf\u0bb2\u0bcd \u0b9a\u0bc6\u0ba9\u0bcd\u0bb1 \u0baa\u0bc6\u0ba3\u0bcd '\u0b95\u0bb0\u0bcb\u0ba9\u0bbe \u0ba8\u0bcb\u0baf\u0bbe\u0bb3\u0bbf' \u0bae\u0bbe\u0baf\u0bae\u0bbe\u0ba9\u0ba4\u0bbf\u0bb2\u0bcd \u0ba4\u0bbf\u0b9f\u0bc0\u0bb0\u0bcd \u0ba4\u0bbf\u0bb0\u0bc1\u0baa\u0bcd\u0baa\u0bae\u0bcd","content":"<p><span style=\"color: rgb(51, 51, 51); font-family: &quot;Noto Sans Tamil&quot;, sans-serif; font-size: 14px; text-align: justify;\">\u0baa\u0bc6\u0b99\u0bcd\u0b95\u0bb3\u0bc2\u0bb0\u0bc1\u0bb5\u0bbf\u0ba9\u0bcd \u0baa\u0bca\u0bae\u0bcd\u0bae\u0ba9\u0bb9\u0bb3\u0bcd\u0bb3\u0bbf \u0baa\u0b95\u0bc1\u0ba4\u0bbf\u0baf\u0bc8\u0b9a\u0bcd \u0b9a\u0bc7\u0bb0\u0bcd\u0ba8\u0bcd\u0ba4 28 \u0bb5\u0baf\u0ba4\u0bbe\u0ba9 \u0b9a\u0b99\u0bcd\u0b95\u0bc0\u0ba4\u0bbe (\u0baa\u0bc6\u0baf\u0bb0\u0bcd \u0bae\u0bbe\u0bb1\u0bcd\u0bb1\u0baa\u0bcd\u0baa\u0b9f\u0bcd\u0b9f\u0bc1\u0bb3\u0bcd\u0bb3\u0ba4\u0bc1) \u0b95\u0bb0\u0bcb\u0ba9\u0bbe \u0b89\u0bb1\u0bc1\u0ba4\u0bbf \u0b9a\u0bc6\u0baf\u0bcd\u0baf\u0baa\u0bcd\u0baa\u0b9f\u0bcd\u0b9f\u0bc1 \u0b86\u0bae\u0bcd\u0baa\u0bc1\u0bb2\u0ba9\u0bcd\u0bb8\u0bbf\u0bb2\u0bcd \u0bae\u0bb0\u0bc1\u0ba4\u0bcd\u0ba4\u0bc1\u0bb5\u0bae\u0ba9\u0bc8\u0b95\u0bcd\u0b95\u0bc1\u0b95\u0bcd \u0b95\u0bca\u0ba3\u0bcd\u0b9f\u0bc1 \u0b9a\u0bc6\u0bb2\u0bcd\u0bb2\u0baa\u0bcd\u0baa\u0b9f\u0bcd\u0b9f \u0ba8\u0bbf\u0bb2\u0bc8\u0baf\u0bbf\u0bb2\u0bcd \u0bae\u0bbe\u0baf\u0bae\u0bbe\u0b95\u0bbf\u0baf\u0bc1\u0bb3\u0bcd\u0bb3\u0bbe\u0bb0\u0bcd. <a href=\"https:\/\/www.dinamani.com\/india\/2020\/sep\/10\/covid-positive-woman-in-bengaluru-goes-missing-after-ambulance-picks-her-up-3462505.html\" target=\"_blank\"><span style=\"color: rgb(255, 0, 0);\">\u0bb5\u0bbf\u0bb0\u0bbf\u0bb5\u0bbe\u0ba9 \u0b9a\u0bc6\u0baf\u0bcd\u0ba4\u0bbf\u0b95\u0bcd\u0b95\u0bc1..<\/span><\/a><\/span><\/p>","date":"2020-09-10 03:04:13","pin":"0","status":1},{"title":"\u0b9a\u0bc6\u0ba9\u0bcd\u0ba9\u0bc8\u0baf\u0bbf\u0bb2\u0bcd \u0b95\u0bb0\u0bcb\u0ba9\u0bbe \u0baa\u0bbe\u0ba4\u0bbf\u0ba4\u0bcd\u0ba4 1.44 \u0bb2\u0b9f\u0bcd\u0b9a\u0bae\u0bcd \u0baa\u0bc7\u0bb0\u0bbf\u0bb2\u0bcd 1.30 \u0bb2\u0b9f\u0bcd\u0b9a\u0bae\u0bcd \u0baa\u0bc7\u0bb0\u0bcd \u0b95\u0bc1\u0ba3\u0bae\u0b9f\u0bc8\u0ba8\u0bcd\u0ba4\u0ba9\u0bb0\u0bcd","content":"<p>&nbsp;\u0b9a\u0bc6\u0ba9\u0bcd\u0ba9\u0bc8\u0baf\u0bbf\u0bb2\u0bcd \u0bb5\u0bbf\u0baf\u0bbe\u0bb4\u0b95\u0bcd\u0b95\u0bbf\u0bb4\u0bae\u0bc8 \u0b95\u0bbe\u0bb2\u0bc8 \u0ba8\u0bbf\u0bb2\u0bb5\u0bb0\u0baa\u0bcd\u0baa\u0b9f\u0bbf, \u0b92\u0b9f\u0bcd\u0b9f\u0bc1\u0bae\u0bca\u0ba4\u0bcd\u0ba4\u0bae\u0bbe\u0b95 \u0b95\u0bb0\u0bcb\u0ba9\u0bbe \u0baa\u0bbe\u0ba4\u0bbf\u0ba4\u0bcd\u0ba4 1,44,595 \u0baa\u0bc7\u0bb0\u0bbf\u0bb2\u0bcd, 1,30,831 \u0baa\u0bc7\u0bb0\u0bcd \u0b95\u0bc1\u0ba3\u0bae\u0b9f\u0bc8\u0ba8\u0bcd\u0ba4\u0bc1\u0bb3\u0bcd\u0bb3\u0ba9\u0bb0\u0bcd. \u0ba4\u0bb1\u0bcd\u0baa\u0bcb\u0ba4\u0bc1 10,854 \u0baa\u0bc7\u0bb0\u0bcd \u0b9a\u0bbf\u0b95\u0bbf\u0b9a\u0bcd\u0b9a\u0bc8\u0baf\u0bbf\u0bb2\u0bcd \u0b89\u0bb3\u0bcd\u0bb3\u0ba9\u0bb0\u0bcd. <a href=\"https:\/\/www.dinamani.com\/tamilnadu\/2020\/sep\/10\/of-the-144-lakh-people-affected-by-corona-in-chennai-130-lakh-have-recovered-3462500.html\" target=\"_blank\"><span style=\"color: rgb(255, 0, 0);\">\u0bb5\u0bbf\u0bb0\u0bbf\u0bb5\u0bbe\u0ba9 \u0b9a\u0bc6\u0baf\u0bcd\u0ba4\u0bbf\u0b95\u0bcd\u0b95\u0bc1..<\/span><\/a><\/p>","date":"2020-09-10 03:05:29","pin":"0","status":1},{"title":"\u0b92\u0bb0\u0bc1\u0ba8\u0bbe\u0bb3\u0bcd \u0b95\u0bb0\u0bcb\u0ba9\u0bbe \u0baa\u0bbe\u0ba4\u0bbf\u0baa\u0bcd\u0baa\u0bbf\u0bb2\u0bcd 60% \u0baa\u0bc7\u0bb0\u0bcd 5 \u0bae\u0bbe\u0ba8\u0bbf\u0bb2\u0b99\u0bcd\u0b95\u0bb3\u0bc8\u0b9a\u0bcd \u0b9a\u0bc7\u0bb0\u0bcd\u0ba8\u0bcd\u0ba4\u0bb5\u0bb0\u0bcd\u0b95\u0bb3\u0bcd: \u0bae\u0ba4\u0bcd\u0ba4\u0bbf\u0baf \u0b9a\u0bc1\u0b95\u0bbe\u0ba4\u0bbe\u0bb0\u0ba4\u0bcd\u0ba4\u0bc1\u0bb1\u0bc8","content":"<p><span style=\"color: rgb(51, 51, 51); font-family: &quot;Noto Sans Tamil&quot;, sans-serif; font-size: 14px; text-align: justify;\">\u0ba8\u0bbe\u0b9f\u0bcd\u0b9f\u0bbf\u0bb2\u0bcd \u0b95\u0b9f\u0ba8\u0bcd\u0ba4 24 \u0bae\u0ba3\u0bbf \u0ba8\u0bc7\u0bb0\u0ba4\u0bcd\u0ba4\u0bbf\u0bb2\u0bcd \u0b8f\u0bb1\u0bcd\u0baa\u0b9f\u0bcd\u0b9f \u0b95\u0bb0\u0bcb\u0ba9\u0bbe \u0baa\u0bbe\u0ba4\u0bbf\u0baa\u0bcd\u0baa\u0bbf\u0bb2\u0bcd 60 \u0b9a\u0ba4\u0bb5\u0bbf\u0b95\u0bbf\u0ba4\u0bae\u0bcd&nbsp; \u0baa\u0bbe\u0ba4\u0bbf\u0baa\u0bcd\u0baa\u0bc1 \u0bae\u0b95\u0bbe\u0bb0\u0bbe\u0bb7\u0bcd\u0bb0\u0bae\u0bcd, \u0b86\u0ba8\u0bcd\u0ba4\u0bbf\u0bb0\u0bae\u0bcd \u0b89\u0bb3\u0bcd\u0bb3\u0bbf\u0b9f\u0bcd\u0b9f 5 \u0bae\u0bbe\u0ba8\u0bbf\u0bb2\u0b99\u0bcd\u0b95\u0bb3\u0bbf\u0bb2\u0bcd \u0b8f\u0bb1\u0bcd\u0baa\u0b9f\u0bcd\u0b9f\u0bc1\u0bb3\u0bcd\u0bb3\u0ba4\u0bbe\u0b95 \u0bae\u0ba4\u0bcd\u0ba4\u0bbf\u0baf \u0b9a\u0bc1\u0b95\u0bbe\u0ba4\u0bbe\u0bb0\u0ba4\u0bcd \u0ba4\u0bc1\u0bb1\u0bc8 \u0ba4\u0b95\u0bb5\u0bb2\u0bcd \u0ba4\u0bc6\u0bb0\u0bbf\u0bb5\u0bbf\u0ba4\u0bcd\u0ba4\u0bc1\u0bb3\u0bcd\u0bb3\u0ba4\u0bc1.&nbsp;<a href=\"https:\/\/www.dinamani.com\/india\/2020\/sep\/10\/60-cases-in-last-24-hours-from-5-states-maharashtra-andhra-top-contributors-3462507.html\"><span style=\"color: rgb(255, 0, 0);\">\u0bb5\u0bbf\u0bb0\u0bbf\u0bb5\u0bbe\u0ba9 \u0b9a\u0bc6\u0baf\u0bcd\u0ba4\u0bbf\u0b95\u0bcd\u0b95\u0bc1..<\/span><\/a><\/span><\/p>\n<div>&nbsp;<\/div>","date":"2020-09-10 05:48:29","pin":"0","status":1},{"title":"\u0ba8\u0bc0\u0b9f\u0bcd \u0ba4\u0bc7\u0bb0\u0bcd\u0bb5\u0bc1: \u0bae\u0bc7\u0bb1\u0bcd\u0b95\u0bc1 \u0bb5\u0b99\u0bcd\u0b95\u0ba4\u0bcd\u0ba4\u0bbf\u0bb2\u0bcd \u0b9a\u0bc6\u0baa\u0bcd.12-\u0b86\u0bae\u0bcd \u0ba4\u0bc7\u0ba4\u0bbf \u0bae\u0bc1\u0bb4\u0bc1 \u0baa\u0bca\u0ba4\u0bc1\u0bae\u0bc1\u0b9f\u0b95\u0bcd\u0b95\u0bae\u0bcd \u0bb0\u0ba4\u0bcd\u0ba4\u0bc1","content":"<p><span style=\"color: rgb(51, 51, 51); font-family: &quot;Noto Sans Tamil&quot;, sans-serif; font-size: 14px; text-align: justify;\">\u0ba8\u0bc0\u0b9f\u0bcd \u0ba4\u0bc7\u0bb0\u0bcd\u0bb5\u0bc1 \u0ba8\u0b9f\u0bc8\u0baa\u0bc6\u0bb1\u0bc1\u0bb5\u0ba4\u0bc8\u0baf\u0bca\u0b9f\u0bcd\u0b9f\u0bbf, \u0bae\u0bc7\u0bb1\u0bcd\u0b95\u0bc1 \u0bb5\u0b99\u0bcd\u0b95\u0ba4\u0bcd\u0ba4\u0bbf\u0bb2\u0bcd&nbsp;\u0b9a\u0bc6\u0baa\u0bcd\u0b9f\u0bae\u0bcd\u0baa\u0bb0\u0bcd 12-\u0b86\u0bae\u0bcd \u0ba4\u0bc7\u0ba4\u0bbf \u0b85\u0bb1\u0bbf\u0bb5\u0bbf\u0b95\u0bcd\u0b95\u0baa\u0bcd\u0baa\u0b9f\u0bcd\u0b9f \u0bae\u0bc1\u0bb4\u0bc1&nbsp;\u0baa\u0bca\u0ba4\u0bc1 \u0bae\u0bc1\u0b9f\u0b95\u0bcd\u0b95\u0bae\u0bcd \u0bb0\u0ba4\u0bcd\u0ba4\u0bc1 \u0b9a\u0bc6\u0baf\u0bcd\u0baf\u0baa\u0bcd\u0baa\u0b9f\u0bc1\u0bb5\u0ba4\u0bbe\u0b95 \u0bae\u0bc1\u0ba4\u0bb2\u0bcd\u0bb5\u0bb0\u0bcd \u0bae\u0bae\u0bcd\u0ba4\u0bbe \u0baa\u0bbe\u0ba9\u0bb0\u0bcd\u0b9c\u0bbf \u0b85\u0bb1\u0bbf\u0bb5\u0bbf\u0ba4\u0bcd\u0ba4\u0bc1\u0bb3\u0bcd\u0bb3\u0bbe\u0bb0\u0bcd.&nbsp;<a href=\"https:\/\/www.dinamani.com\/india\/2020\/sep\/10\/mamata-banerjee-says-no-lockdown-in-west-bengal-on-september-12-3462516.html\"><span style=\"color: rgb(255, 0, 0);\">\u0bb5\u0bbf\u0bb0\u0bbf\u0bb5\u0bbe\u0ba9 \u0b9a\u0bc6\u0baf\u0bcd\u0ba4\u0bbf\u0b95\u0bcd\u0b95\u0bc1..<\/span><\/a><\/span><\/p>\n<div>&nbsp;<\/div>","date":"2020-09-10 05:49:03","pin":"0","status":1},{"title":"\u0bb0\u0bb7\u0bbf\u0baf\u0bbe\u0bb5\u0bbf\u0bb2\u0bcd \u0baa\u0bc1\u0ba4\u0bbf\u0ba4\u0bbe\u0b95 5,363 \u0baa\u0bc7\u0bb0\u0bc1\u0b95\u0bcd\u0b95\u0bc1 \u0ba4\u0bca\u0bb1\u0bcd\u0bb1\u0bc1; \u0b92\u0bb0\u0bc7\u0ba8\u0bbe\u0bb3\u0bbf\u0bb2\u0bcd 128 \u0baa\u0bc7\u0bb0\u0bcd \u0baa\u0bb2\u0bbf","content":"<p><span style=\"color: rgb(51, 51, 51); font-family: &quot;Noto Sans Tamil&quot;, sans-serif; font-size: 14px; text-align: justify;\">\u0bb0\u0bb7\u0bbf\u0baf\u0bbe\u0bb5\u0bbf\u0bb2\u0bcd \u0baa\u0bc1\u0ba4\u0bbf\u0ba4\u0bbe\u0b95 5,363 \u0baa\u0bc7\u0bb0\u0bc1\u0b95\u0bcd\u0b95\u0bc1 \u0b95\u0bb0\u0bcb\u0ba9\u0bbe \u0ba4\u0bca\u0bb1\u0bcd\u0bb1\u0bc1 \u0b89\u0bb1\u0bc1\u0ba4\u0bbf\u0baf\u0bbe\u0b95\u0bbf\u0baf\u0bc1\u0bb3\u0bcd\u0bb3\u0ba4\u0bc1. \u0bae\u0bc7\u0bb2\u0bc1\u0bae\u0bcd 128 \u0baa\u0bc7\u0bb0\u0bcd \u0baa\u0bb2\u0bbf\u0baf\u0bbe\u0b95\u0bbf\u0baf\u0bc1\u0bb3\u0bcd\u0bb3\u0ba9\u0bb0\u0bcd.&nbsp;<a href=\"https:\/\/www.dinamani.com\/world\/2020\/sep\/10\/russia-registered-5363-new-covid-19-cases-in-the-past-24-hours-3462534.html\"><span style=\"color: rgb(255, 0, 0);\">\u0bb5\u0bbf\u0bb0\u0bbf\u0bb5\u0bbe\u0ba9 \u0b9a\u0bc6\u0baf\u0bcd\u0ba4\u0bbf\u0b95\u0bcd\u0b95\u0bc1..<\/span><\/a><\/span><\/p>\n<div>&nbsp;<\/div>","date":"2020-09-10 05:49:37","pin":"0","status":1},{"title":"\u0ba4\u0bae\u0bbf\u0bb4\u0b95\u0ba4\u0bcd\u0ba4\u0bbf\u0bb2\u0bcd \u0bae\u0bc7\u0bb2\u0bc1\u0bae\u0bcd 5,528 \u0baa\u0bc7\u0bb0\u0bc1\u0b95\u0bcd\u0b95\u0bc1 \u0ba4\u0bca\u0bb1\u0bcd\u0bb1\u0bc1 \u0b89\u0bb1\u0bc1\u0ba4\u0bbf; \u0b92\u0bb0\u0bc7\u0ba8\u0bbe\u0bb3\u0bbf\u0bb2\u0bcd 64 \u0baa\u0bc7\u0bb0\u0bcd \u0baa\u0bb2\u0bbf","content":"<p><span style=\"color: rgb(51, 51, 51); font-family: &quot;Noto Sans Tamil&quot;, sans-serif; font-size: 14px; text-align: justify;\">\u0ba4\u0bae\u0bbf\u0bb4\u0b95\u0ba4\u0bcd\u0ba4\u0bbf\u0bb2\u0bcd \u0baa\u0bc1\u0ba4\u0bbf\u0ba4\u0bbe\u0b95 5,528 \u0baa\u0bc7\u0bb0\u0bc1\u0b95\u0bcd\u0b95\u0bc1 \u0b95\u0bb0\u0bcb\u0ba9\u0bbe \u0bb5\u0bc8\u0bb0\u0bb8\u0bcd \u0ba4\u0bca\u0bb1\u0bcd\u0bb1\u0bc1 \u0b87\u0bb0\u0bc1\u0baa\u0bcd\u0baa\u0ba4\u0bc1 \u0b87\u0ba9\u0bcd\u0bb1\u0bc1 (\u0b9a\u0bc6\u0baa\u0bcd.10, \u0bb5\u0bbf\u0baf\u0bbe\u0bb4\u0b95\u0bcd\u0b95\u0bbf\u0bb4\u0bae\u0bc8) \u0b89\u0bb1\u0bc1\u0ba4\u0bbf \u0b9a\u0bc6\u0baf\u0bcd\u0baf\u0baa\u0bcd\u0baa\u0b9f\u0bcd\u0b9f\u0bc1\u0bb3\u0bcd\u0bb3\u0ba4\u0bc1. \u0bae\u0bc7\u0bb2\u0bc1\u0bae\u0bcd 64 \u0baa\u0bc7\u0bb0\u0bcd \u0b89\u0baf\u0bbf\u0bb0\u0bbf\u0bb4\u0ba8\u0bcd\u0ba4\u0bc1\u0bb3\u0bcd\u0bb3\u0ba9\u0bb0\u0bcd.&nbsp;<\/span><font color=\"#333333\" face=\"Noto Sans Tamil, sans-serif\"><span style=\"font-size: 14px;\"><a href=\"https:\/\/www.dinamani.com\/tamilnadu\/2020\/sep\/10\/corona-update-5528-new-cases-in-tamil-nadu-3462563.html\"><span style=\"color: rgb(255, 0, 0);\">\u0bb5\u0bbf\u0bb0\u0bbf\u0bb5\u0bbe\u0ba9 \u0b9a\u0bc6\u0baf\u0bcd\u0ba4\u0bbf\u0b95\u0bcd\u0b95\u0bc1..<\/span><\/a><\/span><\/font><\/p>","date":"2020-09-10 06:10:16","pin":"0","status":1},{"title":"\u0b9a\u0bc6\u0ba9\u0bcd\u0ba9\u0bc8\u0baf\u0bbf\u0bb2\u0bcd 991 \u0baa\u0bc7\u0bb0\u0bcd; \u0baa\u0bbf\u0bb1 \u0bae\u0bbe\u0bb5\u0b9f\u0bcd\u0b9f\u0b99\u0bcd\u0b95\u0bb3\u0bbf\u0bb2\u0bcd 4,537 \u0baa\u0bc7\u0bb0\u0bcd: \u0bae\u0bbe\u0bb5\u0b9f\u0bcd\u0b9f\u0bb5\u0bbe\u0bb0\u0bbf\u0baf\u0bbe\u0b95 \u0b95\u0bb0\u0bcb\u0ba9\u0bbe \u0baa\u0bbe\u0ba4\u0bbf\u0baa\u0bcd\u0baa\u0bc1 \u0bb5\u0bbf\u0bb5\u0bb0\u0bae\u0bcd","content":"<p><span style=\"color: rgb(51, 51, 51); font-family: &quot;Noto Sans Tamil&quot;, sans-serif; font-size: 14px; text-align: justify;\">\u0b9a\u0bc6\u0ba9\u0bcd\u0ba9\u0bc8 \u0ba4\u0bb5\u0bbf\u0bb0\u0bcd\u0ba4\u0bcd\u0ba4\u0bc1 \u0ba4\u0bae\u0bbf\u0bb4\u0b95\u0ba4\u0bcd\u0ba4\u0bbf\u0ba9\u0bcd \u0baa\u0bbf\u0bb1 \u0bae\u0bbe\u0bb5\u0b9f\u0bcd\u0b9f\u0b99\u0bcd\u0b95\u0bb3\u0bbf\u0bb2\u0bcd \u0b87\u0ba9\u0bcd\u0bb1\u0bc1 4,537 \u0baa\u0bc7\u0bb0\u0bc1\u0b95\u0bcd\u0b95\u0bc1 \u0b95\u0bb0\u0bcb\u0ba9\u0bbe \u0ba4\u0bca\u0bb1\u0bcd\u0bb1\u0bc1 \u0b87\u0bb0\u0bc1\u0baa\u0bcd\u0baa\u0ba4\u0bc1 \u0b89\u0bb1\u0bc1\u0ba4\u0bbf \u0b86\u0b95\u0bbf\u0baf\u0bc1\u0bb3\u0bcd\u0bb3\u0ba4\u0bc1. <a href=\"https:\/\/www.dinamani.com\/tamilnadu\/2020\/sep\/10\/chennai-reports-991-new-corona-cases-today-district-wise-update-3462569.html\"><span style=\"color: rgb(255, 0, 0);\">\u0bb5\u0bbf\u0bb0\u0bbf\u0bb5\u0bbe\u0ba9 \u0b9a\u0bc6\u0baf\u0bcd\u0ba4\u0bbf\u0b95\u0bcd\u0b95\u0bc1..<\/span><\/a><\/span><\/p>\n<div>&nbsp;<\/div>","date":"2020-09-10 06:20:01","pin":"0","status":1},{"title":"\u0ba4\u0bbf\u0bb2\u0bcd\u0bb2\u0bbf\u0baf\u0bbf\u0bb2\u0bcd \u0baa\u0bc1\u0ba4\u0bbf\u0ba4\u0bbe\u0b95 4308 \u0baa\u0bc7\u0bb0\u0bc1\u0b95\u0bcd\u0b95\u0bc1 \u0b95\u0bb0\u0bcb\u0ba9\u0bbe; \u0bae\u0bc7\u0bb2\u0bc1\u0bae\u0bcd 28 \u0baa\u0bc7\u0bb0\u0bcd \u0baa\u0bb2\u0bbf","content":"<p><span style=\"color: rgb(51, 51, 51); font-family: &quot;Noto Sans Tamil&quot;, sans-serif; font-size: 14px; text-align: justify;\">\u0ba4\u0bb2\u0bc8\u0ba8\u0b95\u0bbe\u0bcd \u0ba4\u0bbf\u0bb2\u0bcd\u0bb2\u0bbf\u0baf\u0bbf\u0bb2\u0bcd \u0b87\u0ba9\u0bcd\u0bb1\u0bc1 \u0bae\u0bc7\u0bb2\u0bc1\u0bae\u0bcd 4308 \u0baa\u0bc7\u0bb0\u0bc1\u0b95\u0bcd\u0b95\u0bc1 \u0b95\u0bb0\u0bcb\u0ba9\u0bbe \u0ba4\u0bca\u0bb1\u0bcd\u0bb1\u0bc1 \u0b89\u0bb1\u0bc1\u0ba4\u0bbf \u0b9a\u0bc6\u0baf\u0bcd\u0baf\u0baa\u0bcd\u0baa\u0b9f\u0bcd\u0b9f\u0bc1\u0bb3\u0bcd\u0bb3\u0ba4\u0bc1.&nbsp;<\/span><\/p>\n<div>&nbsp;<\/div>\n<div id=\"mwayss_div_2008685213\" class=\"mwayss_div\" style=\"box-sizing: border-box; margin: 0px; color: rgb(51, 51, 51); font-family: &quot;Noto Sans Tamil&quot;, sans-serif; font-size: 0px; line-height: 0;\">\n<div id=\"mwayss_div_8010549903\" class=\"mwayss_div\" style=\"box-sizing: border-box; margin: 0px; line-height: 0;\">&nbsp;<\/div>\n<\/div>","date":"2020-09-10 08:23:57","pin":"0","status":1},{"title":"\u0bae\u0b95\u0bbe\u0bb0\u0bbe\u0bb7\u0bcd\u0b9f\u0bbf\u0bb0\u0ba4\u0bcd\u0ba4\u0bbf\u0bb2\u0bcd \u0b92\u0bb0\u0bc7\u0ba8\u0bbe\u0bb3\u0bbf\u0bb2\u0bcd 23,446 \u0baa\u0bc7\u0bb0\u0bc1\u0b95\u0bcd\u0b95\u0bc1 \u0b95\u0bb0\u0bcb\u0ba9\u0bbe; 448 \u0baa\u0bc7\u0bb0\u0bcd \u0baa\u0bb2\u0bbf","content":"<p><span style=\"color: rgb(51, 51, 51); font-family: &quot;Noto Sans Tamil&quot;, sans-serif; font-size: 14px; text-align: justify;\">\u0bae\u0b95\u0bbe\u0bb0\u0bbe\u0bb7\u0bcd\u0b9f\u0bbf\u0bb0\u0ba4\u0bcd\u0ba4\u0bbf\u0bb2\u0bcd \u0b92\u0bb0\u0bc7\u0ba8\u0bbe\u0bb3\u0bbf\u0bb2\u0bcd 23,446 \u0baa\u0bc7\u0bb0\u0bc1\u0b95\u0bcd\u0b95\u0bc1 \u0b95\u0bb0\u0bcb\u0ba9\u0bbe \u0ba4\u0bca\u0bb1\u0bcd\u0bb1\u0bc1 \u0b89\u0bb1\u0bc1\u0ba4\u0bbf \u0b9a\u0bc6\u0baf\u0bcd\u0baf\u0baa\u0bcd\u0baa\u0b9f\u0bcd\u0b9f\u0bc1\u0bb3\u0bcd\u0bb3\u0ba4\u0bc1.&nbsp;<\/span><\/p>\n<div>&nbsp;<\/div>\n<div id=\"vdo_ai_div-0\" style=\"box-sizing: border-box; margin: 0px; color: rgb(51, 51, 51); font-family: &quot;Noto Sans Tamil&quot;, sans-serif; font-size: 13px; width: 764.979px;\">&nbsp;<\/div>","date":"2020-09-10 09:34:31","pin":"0","status":1}]}